simplepyds/__init__.py
simplepyds/Base/Container.py
simplepyds/Base/__init__.py
simplepyds/Errors/CustomErrors.py
simplepyds/Errors/__init__.py
simplepyds/HashTable/HashTable.py
simplepyds/HashTable/__init__.py
simplepyds/LinkedList/DoublyLinkedList.py
simplepyds/LinkedList/Node.py
simplepyds/LinkedList/SinglyLinkedList.py
simplepyds/LinkedList/__init__.py
simplepyds/Queue/Queue.py
simplepyds/Queue/__init__.py
simplepyds/Stack/Stack.py
simplepyds/Stack/__init__.py
simplepyds/Tree/BinarySearchTree.py
simplepyds/Tree/TreeNode.py
simplepyds/Tree/__init__.py
simplepyds-0.0.4.dist-info/LICENSE
simplepyds-0.0.4.dist-info/METADATA
simplepyds-0.0.4.dist-info/WHEEL
simplepyds-0.0.4.dist-info/top_level.txt
simplepyds-0.0.4.dist-info/RECORD
