Metadata-Version: 2.1
Name: simplepyds
Version: 0.0.4
Summary: A Collection of Simple Data Structures
Author: Theophilus Nenhanga
Author-email: theonenhanga@gmail.com
Keywords: data structures
Classifier: Programming Language :: Python :: 3.12
Classifier: Operating System :: MacOS :: MacOS X
Classifier: Operating System :: Microsoft :: Windows
License-File: LICENSE
Requires-Dist: typing
